rformat.py
rformat-0.2.0.dist-info/DESCRIPTION.rst
rformat-0.2.0.dist-info/METADATA
rformat-0.2.0.dist-info/metadata.json
rformat-0.2.0.dist-info/RECORD
rformat-0.2.0.dist-info/top_level.txt
rformat-0.2.0.dist-info/WHEEL
rformat-0.2.0.dist-info/zip-safe
