Metadata-Version: 2.0
Name: rformat
Version: 0.2.0
Summary: rformat is a recursive version of str.format
Home-page: UNKNOWN
Author: brian wickman
Author-email: wickman@gmail.com
License: MIT
Platform: UNKNOWN
